type_extensions/__init__.py
type_extensions/_type_extensions.py
type_extensions-0.1.2.dist-info/AUTHORS.rst
type_extensions-0.1.2.dist-info/LICENSE.txt
type_extensions-0.1.2.dist-info/METADATA
type_extensions-0.1.2.dist-info/WHEEL
type_extensions-0.1.2.dist-info/top_level.txt
type_extensions-0.1.2.dist-info/RECORD
