Metadata-Version: 2.1
Name: type_extensions
Version: 0.1.2
Summary: Importable mixin methods for Python.
Home-page: https://github.com/quansight/type_extensions/
Author: David Charboneau
Author-email: david@adadabase.com
License: mit
Platform: any
Classifier: Development Status :: 4 - Beta
Classifier: Programming Language :: Python
Classifier: Topic :: Software Development
Classifier: Typing :: Typed
Provides-Extra: testing
